.pre-commit-config.yaml
CHANGES.rst
CODE_OF_CONDUCT.md
LICENSE
mkkey/__init__.py
mkkey/__main__.py
mkkey/cli.py
mkkey/completion.py
mkkey/jwk.py
mkkey/paserk.py
mkkey/py.typed
mkkey/utils.py
tox.ini
mkkey-0.7.2.dist-info/LICENSE
mkkey-0.7.2.dist-info/METADATA
mkkey-0.7.2.dist-info/WHEEL
mkkey-0.7.2.dist-info/entry_points.txt
mkkey-0.7.2.dist-info/RECORD
