Metadata-Version: 2.1
Name: mkkey
Version: 0.7.2
Summary: An Application-Layer Key (JWK/PASERK) Generator
Home-page: https://github.com/dajiaji/mkkey
License: MIT
Author: Ajitomi Daisuke
Author-email: dajiaji@gmail.com
Requires-Python: >=3.8,<4.0
Classifier: License :: OSI Approved :: MIT License
Classifier: Programming Language :: Python :: 3
Classifier: Programming Language :: Python :: 3.8
Classifier: Programming Language :: Python :: 3.9
Classifier: Programming Language :: Python :: 3.10
Classifier: Programming Language :: Python :: 3.11
Classifier: Programming Language :: Python :: 3.12
Requires-Dist: click (>=8.1.7,<9.0.0)
Requires-Dist: click-help-colors (>=0.9.2,<0.10.0)
Requires-Dist: cryptography (>=42.0.1,<43.0.0)
Requires-Dist: pyseto (>=1.7.8,<2.0.0)
Requires-Dist: shellingham (>=1.5.3,<2.0.0)
Project-URL: Repository, https://github.com/dajiaji/mkkey
